mercuryitc/__init__.py
mercuryitc/mercury_driver.py
mercuryitc-0.3.0.dist-info/LICENSE.txt
mercuryitc-0.3.0.dist-info/METADATA
mercuryitc-0.3.0.dist-info/WHEEL
mercuryitc-0.3.0.dist-info/top_level.txt
mercuryitc-0.3.0.dist-info/RECORD
