Metadata-Version: 2.1
Name: mercuryitc
Version: 0.3.0
Summary: Full Python driver for the Oxford Mercury iTC cryogenic environment controller.
Home-page: https://github.com/crazyfermions/python-mercury_driver
Author: Florian Forster, Sam Schott
Maintainer: Florian Forster
Maintainer-email: florian.forster@rwth-aachen.de
License: MIT
Platform: UNKNOWN
Requires-Python: >=3.6
Requires-Dist: PyVISA
Requires-Dist: pyvisa-py
